summary_stats/__init__.py
summary_stats/stats.py
summary_stats-0.1.0.dist-info/LICENSE
summary_stats-0.1.0.dist-info/METADATA
summary_stats-0.1.0.dist-info/WHEEL
summary_stats-0.1.0.dist-info/top_level.txt
summary_stats-0.1.0.dist-info/RECORD
